<?xml version="1.0" encoding="utf-8"?>
<LipSyncVisemes wavFile="TTS-551CDF1D4795762CC49F7935E9F2C834.wav">
  <viseme type="7" time="0.085" duration="0.045" />
  <viseme type="4" time="0.13" duration="0.04" />
  <viseme type="19" time="0.17" duration="0.035" />
  <viseme type="2" time="0.205" duration="0.045" />
  <viseme type="6" time="0.25" duration="0.045" />
  <viseme type="7" time="0.295" duration="0.065" />
  <viseme type="4" time="0.36" duration="0.07" />
  <viseme type="19" time="0.43" duration="0.04" />
  <viseme type="19" time="0.47" duration="0.04" />
  <viseme type="2" time="0.51" duration="0.087" />
  <viseme type="4" time="0.597" duration="0.087" />
  <viseme type="19" time="0.684" duration="0.075" />
  <viseme type="4" time="1.114" duration="0.085" />
  <viseme type="18" time="1.199" duration="0.05" />
  <viseme type="13" time="1.249" duration="0.035" />
  <viseme type="6" time="1.284" duration="0.05" />
  <viseme type="19" time="1.334" duration="0.08" />
  <viseme type="6" time="1.414" duration="0.045" />
  <viseme type="20" time="1.459" duration="0.075" />
  <viseme type="7" time="1.534" duration="0.035" />
  <viseme type="1" time="1.569" duration="0.035" />
  <viseme type="15" time="1.604" duration="0.07" />
  <viseme type="18" time="1.674" duration="0.08" />
  <viseme type="2" time="1.754" duration="0.087" />
  <viseme type="6" time="1.841" duration="0.087" />
  <viseme type="19" time="1.928" duration="0.105" />
  <viseme type="2" time="2.788" duration="0.05" />
  <viseme type="6" time="2.838" duration="0.05" />
  <viseme type="19" time="2.888" duration="0.05" />
  <viseme type="8" time="2.938" duration="0.09" />
  <viseme type="19" time="3.028" duration="0.04" />
  <viseme type="19" time="3.068" duration="0.045" />
  <viseme type="19" time="3.113" duration="0.045" />
  <viseme type="8" time="3.158" duration="0.125" />
  <viseme type="7" time="3.283" duration="0.06" />
  <viseme type="2" time="3.343" duration="0.045" />
  <viseme type="19" time="3.388" duration="0.04" />
  <viseme type="12" time="3.428" duration="0.055" />
  <viseme type="1" time="3.483" duration="0.075" />
  <viseme type="21" time="3.558" duration="0.055" />
  <viseme type="1" time="3.613" duration="0.075" />
  <viseme type="19" time="3.688" duration="0.1" />
  <viseme type="19" time="3.788" duration="0.07" />
  <viseme type="18" time="4.613" duration="0.085" />
  <viseme type="3" time="4.698" duration="0.05" />
  <viseme type="13" time="4.748" duration="0.05" />
  <viseme type="21" time="4.798" duration="0.065" />
  <viseme type="6" time="4.863" duration="0.105" />
  <viseme type="6" time="4.968" duration="0.055" />
  <viseme type="19" time="5.023" duration="0.035" />
  <viseme type="21" time="5.058" duration="0.045" />
  <viseme type="1" time="5.103" duration="0.065" />
  <viseme type="15" time="5.168" duration="0.065" />
  <viseme type="19" time="5.233" duration="0.04" />
  <viseme type="12" time="5.273" duration="0.025" />
  <viseme type="1" time="5.298" duration="0.04" />
  <viseme type="18" time="5.338" duration="0.04" />
  <viseme type="21" time="5.378" duration="0.075" />
  <viseme type="6" time="5.453" duration="0.045" />
  <viseme type="19" time="5.498" duration="0.055" />
  <viseme type="2" time="5.553" duration="0.035" />
  <viseme type="4" time="5.588" duration="0.035" />
  <viseme type="13" time="5.623" duration="0.04" />
  <viseme type="19" time="5.663" duration="0.065" />
  <viseme type="4" time="5.728" duration="0.045" />
  <viseme type="6" time="5.773" duration="0.045" />
  <viseme type="21" time="5.818" duration="0.04" />
  <viseme type="1" time="5.858" duration="0.04" />
  <viseme type="13" time="5.898" duration="0.115" />
  <viseme type="17" time="6.368" duration="0.035" />
  <viseme type="1" time="6.403" duration="0.055" />
  <viseme type="19" time="6.458" duration="0.055" />
  <viseme type="21" time="6.513" duration="0.06" />
  <viseme type="6" time="6.573" duration="0.075" />
  <viseme type="19" time="6.648" duration="0.042" />
  <viseme type="16" time="6.69" duration="0.042" />
  <viseme type="1" time="6.732" duration="0.065" />
  <viseme type="20" time="6.797" duration="0.06" />
  <viseme type="4" time="6.857" duration="0.13" />
  <viseme type="19" time="6.987" duration="0.125" />
  <viseme type="2" time="7.867" duration="0.04" />
  <viseme type="13" time="7.907" duration="0.075" />
  <viseme type="6" time="7.982" duration="0.075" />
  <viseme type="7" time="8.057" duration="0.06" />
  <viseme type="16" time="8.117" duration="0.125" />
  <viseme type="4" time="8.242" duration="0.05" />
  <viseme type="13" time="8.292" duration="0.08" />
  <viseme type="6" time="8.372" duration="0.055" />
  <viseme type="19" time="8.427" duration="0.045" />
  <viseme type="7" time="8.472" duration="0.035" />
  <viseme type="1" time="8.507" duration="0.045" />
  <viseme type="15" time="8.552" duration="0.07" />
  <viseme type="12" time="8.622" duration="0.06" />
  <viseme type="5" time="8.682" duration="0.08" />
  <viseme type="13" time="8.762" duration="0.135" />
</LipSyncVisemes>