<?xml version="1.0" encoding="utf-8"?>
<LipSyncVisemes wavFile="TTS-64E9C51777978DA8850787F1283043A3.wav">
  <viseme type="12" time="0.085" duration="0.045" />
  <viseme type="5" time="0.13" duration="0.03" />
  <viseme type="13" time="0.16" duration="0.04" />
  <viseme type="19" time="0.2" duration="0.065" />
  <viseme type="4" time="0.265" duration="0.05" />
  <viseme type="6" time="0.315" duration="0.05" />
  <viseme type="21" time="0.365" duration="0.07" />
  <viseme type="4" time="0.435" duration="0.12" />
  <viseme type="15" time="0.555" duration="0.085" />
  <viseme type="21" time="0.64" duration="0.055" />
  <viseme type="1" time="0.695" duration="0.07" />
  <viseme type="13" time="0.765" duration="0.06" />
  <viseme type="6" time="0.825" duration="0.085" />
  <viseme type="1" time="0.91" duration="0.08" />
  <viseme type="1" time="0.99" duration="0.11" />
  <viseme type="19" time="1.1" duration="0.035" />
  <viseme type="1" time="1.135" duration="0.045" />
  <viseme type="14" time="1.18" duration="0.065" />
  <viseme type="4" time="1.245" duration="0.085" />
  <viseme type="6" time="1.33" duration="0.085" />
  <viseme type="19" time="1.415" duration="0.065" />
  <viseme type="21" time="1.835" duration="0.045" />
  <viseme type="1" time="1.88" duration="0.04" />
  <viseme type="19" time="1.92" duration="0.045" />
  <viseme type="7" time="1.965" duration="0.045" />
  <viseme type="6" time="2.01" duration="0.065" />
  <viseme type="20" time="2.075" duration="0.095" />
  <viseme type="3" time="2.17" duration="0.095" />
  <viseme type="14" time="2.265" duration="0.075" />
  <viseme type="12" time="2.34" duration="0.06" />
  <viseme type="5" time="2.4" duration="0.035" />
  <viseme type="13" time="2.435" duration="0.055" />
  <viseme type="14" time="2.49" duration="0.06" />
  <viseme type="4" time="2.55" duration="0.087" />
  <viseme type="6" time="2.637" duration="0.087" />
  <viseme type="14" time="3.079" duration="0.04" />
  <viseme type="2" time="3.119" duration="0.042" />
  <viseme type="6" time="3.161" duration="0.042" />
  <viseme type="20" time="3.203" duration="0.07" />
  <viseme type="17" time="3.273" duration="0.03" />
  <viseme type="1" time="3.303" duration="0.045" />
  <viseme type="19" time="3.348" duration="0.065" />
  <viseme type="3" time="3.413" duration="0.175" />
  <viseme type="20" time="3.588" duration="0.095" />
  <viseme type="2" time="4.038" duration="0.175" />
  <viseme type="2" time="4.568" duration="0.175" />
</LipSyncVisemes>