<?xml version="1.0" encoding="utf-8"?>
<LipSyncVisemes wavFile="TTS-DD21FA9913629AE0247CC7311C957966.wav">
  <viseme type="2" time="0.1" duration="0.06" />
  <viseme type="6" time="0.16" duration="0.06" />
  <viseme type="20" time="0.22" duration="0.115" />
  <viseme type="1" time="0.335" duration="0.11" />
  <viseme type="19" time="0.445" duration="0.04" />
  <viseme type="19" time="0.485" duration="0.04" />
  <viseme type="1" time="0.525" duration="0.065" />
  <viseme type="18" time="0.59" duration="0.09" />
  <viseme type="3" time="0.68" duration="0.095" />
  <viseme type="13" time="0.775" duration="0.07" />
  <viseme type="19" time="0.845" duration="0.045" />
  <viseme type="19" time="0.89" duration="0.05" />
  <viseme type="4" time="0.94" duration="0.055" />
  <viseme type="21" time="0.995" duration="0.05" />
  <viseme type="6" time="1.045" duration="0.105" />
  <viseme type="1" time="1.15" duration="0.105" />
  <viseme type="19" time="1.255" duration="0.055" />
  <viseme type="6" time="1.31" duration="0.065" />
  <viseme type="21" time="1.375" duration="0.06" />
  <viseme type="21" time="1.435" duration="0.075" />
  <viseme type="14" time="1.51" duration="0.065" />
  <viseme type="3" time="1.575" duration="0.097" />
  <viseme type="6" time="1.672" duration="0.097" />
  <viseme type="19" time="1.769" duration="0.11" />
  <viseme type="2" time="2.729" duration="0.062" />
  <viseme type="6" time="2.791" duration="0.062" />
  <viseme type="12" time="2.853" duration="0.085" />
  <viseme type="1" time="2.938" duration="0.075" />
  <viseme type="18" time="3.013" duration="0.045" />
  <viseme type="1" time="3.058" duration="0.065" />
  <viseme type="12" time="3.123" duration="0.085" />
  <viseme type="2" time="3.208" duration="0.065" />
  <viseme type="4" time="3.273" duration="0.065" />
  <viseme type="15" time="3.338" duration="0.085" />
  <viseme type="21" time="3.423" duration="0.075" />
  <viseme type="4" time="3.498" duration="0.065" />
  <viseme type="6" time="3.563" duration="0.065" />
  <viseme type="21" time="3.628" duration="0.045" />
  <viseme type="1" time="3.673" duration="0.07" />
  <viseme type="19" time="3.743" duration="0.05" />
  <viseme type="19" time="3.793" duration="0.115" />
  <viseme type="2" time="4.758" duration="0.062" />
  <viseme type="6" time="4.82" duration="0.062" />
  <viseme type="12" time="4.882" duration="0.085" />
  <viseme type="1" time="4.967" duration="0.075" />
  <viseme type="18" time="5.042" duration="0.06" />
  <viseme type="19" time="5.102" duration="0.065" />
  <viseme type="16" time="5.167" duration="0.065" />
  <viseme type="6" time="5.232" duration="0.075" />
  <viseme type="14" time="5.307" duration="0.08" />
  <viseme type="19" time="5.387" duration="0.055" />
  <viseme type="13" time="5.442" duration="0.055" />
  <viseme type="1" time="5.497" duration="0.065" />
  <viseme type="19" time="5.562" duration="0.145" />
</LipSyncVisemes>