<?xml version="1.0" encoding="utf-8"?>
<LipSyncVisemes wavFile="TTS-7A0DC832ED0A336DF3B3F44F0AC30DD3.wav">
  <viseme type="4" time="0.18690008912656" duration="0.0752015240641711" />
  <viseme type="7" time="0.262101613190731" duration="0.0957558645276292" />
  <viseme type="19" time="0.35785747771836" duration="0.094417798573975" />
  <viseme type="9" time="0.452275276292335" duration="0.121522950089127" />
  <viseme type="18" time="0.573798226381462" duration="0.0237852941176471" />
  <viseme type="6" time="0.597583520499109" duration="0.0948092691622103" />
  <viseme type="20" time="0.692392789661319" duration="0.0239518360071302" />
  <viseme type="1" time="0.716344625668449" duration="0.047738092691622" />
  <viseme type="14" time="0.764082718360071" duration="0.100991978609626" />
  <viseme type="6" time="0.865074696969697" duration="0.0362627450980392" />
  <viseme type="1" time="0.901337442067736" duration="0.157308377896613" />
  <viseme type="15" time="1.05864581996435" duration="0.0358172905525846" />
  <viseme type="7" time="1.09446311051693" duration="0.0300237076648841" />
  <viseme type="14" time="1.12448681818182" duration="0.0690742424242424" />
  <viseme type="21" time="1.19356106060606" duration="0.0446744206773619" />
  <viseme type="14" time="1.23823548128342" duration="0.0985403743315508" />
  <viseme type="4" time="1.33677585561497" duration="0.0884581105169339" />
  <viseme type="15" time="1.42523396613191" duration="0.13357807486631" />
  <viseme type="7" time="1.55881204099822" duration="0.0237858288770054" />
  <viseme type="4" time="2.05699778074866" duration="0.0657308556149732" />
  <viseme type="7" time="2.12272863636364" duration="0.0957558645276293" />
  <viseme type="19" time="2.21848450089127" duration="0.100155793226381" />
  <viseme type="9" time="2.31864029411765" duration="0.113191443850267" />
  <viseme type="18" time="2.43183173796791" duration="0.0529750445632798" />
  <viseme type="1" time="2.48480678253119" duration="0.0637261764705882" />
  <viseme type="14" time="2.54853295900178" duration="0.0872866934046345" />
  <viseme type="1" time="2.63581965240642" duration="0.024788734402852" />
  <viseme type="6" time="2.66060838680927" duration="0.0815926470588235" />
  <viseme type="20" time="2.74220103386809" duration="0.102416532976827" />
  <viseme type="8" time="2.84461756684492" duration="0.0792707664884135" />
  <viseme type="4" time="2.92388833333333" duration="0.0873286987522282" />
  <viseme type="14" time="3.01121703208556" duration="0.0895160427807486" />
  <viseme type="1" time="3.10073307486631" duration="0.153072459893048" />
  <viseme type="6" time="3.25380553475936" duration="0.036820944741533" />
  <viseme type="19" time="3.29062647950089" duration="0.096812834224599" />
  <viseme type="1" time="3.38743931372549" duration="0.0252345811051693" />
  <viseme type="14" time="3.91480338680927" duration="0.0396061853832442" />
  <viseme type="15" time="4.05679377005348" duration="0.0982607486631016" />
  <viseme type="4" time="4.15505451871658" duration="0.0630017914438503" />
  <viseme type="19" time="4.21805631016043" duration="0.0311320499108735" />
  <viseme type="21" time="4.3124874688057" duration="0.132438770053476" />
  <viseme type="4" time="4.44492623885918" duration="0.0568172638146168" />
  <viseme type="19" time="4.5017435026738" duration="0.0471819340463458" />
  <viseme type="4" time="4.54892543672014" duration="0.0627767379679145" />
  <viseme type="14" time="4.61170217468806" duration="0.0557601604278074" />
  <viseme type="1" time="4.66746233511586" duration="0.0613671122994654" />
  <viseme type="15" time="4.72882944741533" duration="0.0793679144385026" />
  <viseme type="19" time="4.80819736185383" duration="0.0867879679144385" />
  <viseme type="2" time="4.89498532976827" duration="0.0857299465240642" />
  <viseme type="15" time="4.98071527629233" duration="0.0335358288770053" />
  <viseme type="20" time="5.11641242424242" duration="0.0789322638146168" />
  <viseme type="8" time="5.19534468805704" duration="0.0766488413547238" />
  <viseme type="21" time="5.27199352941176" duration="0.0442282531194295" />
  <viseme type="7" time="5.31622178253119" duration="0.0541167557932263" />
  <viseme type="14" time="5.37033853832442" duration="0.0573409982174689" />
  <viseme type="19" time="5.42767953654189" duration="0.0872616755793225" />
  <viseme type="1" time="5.51494121212121" duration="0.0364346702317291" />
  <viseme type="19" time="5.55137588235294" duration="0.0378139928698752" />
  <viseme type="7" time="5.58918987522282" duration="0.0866950980392156" />
  <viseme type="21" time="5.67588497326203" duration="0.206406773618538" />
  <viseme type="2" time="5.88229174688057" duration="0.0305812834224599" />
</LipSyncVisemes>