<?xml version="1.0" encoding="utf-8"?>
<LipSyncVisemes wavFile="3058728181.wav">
  <viseme type="13" time="0.004" duration="0.089" />
  <viseme type="11" time="0.093" duration="0.1" />
  <viseme type="19" time="0.193" duration="0.09" />
  <viseme type="19" time="0.283" duration="0.049" />
  <viseme type="3" time="0.332" duration="0.128" />
  <viseme type="19" time="0.46" duration="0.081" />
  <viseme type="4" time="0.541" duration="0.156" />
  <viseme type="14" time="0.697" duration="0.099" />
  <viseme type="6" time="0.796" duration="0.127" />
  <viseme type="19" time="0.923" duration="0.119" />
  <viseme type="6" time="1.042" duration="0.13" />
  <viseme type="21" time="1.172" duration="0.083" />
  <viseme type="6" time="1.255" duration="0.096" />
  <viseme type="19" time="1.351" duration="0.119" />
  <viseme type="13" time="1.47" duration="0.049" />
  <viseme type="11" time="1.519" duration="0.16" />
  <viseme type="19" time="1.679" duration="0.079" />
  <viseme type="3" time="1.758" duration="0.109" />
  <viseme type="19" time="1.867" duration="0.029" />
  <viseme type="19" time="1.896" duration="0.079" />
  <viseme type="8" time="1.975" duration="0.215" />
  <viseme type="21" time="2.19" duration="0.09" />
  <viseme type="19" time="2.28" duration="0.104" />
  <viseme type="3" time="2.384" duration="0.12" />
  <viseme type="19" time="2.504" duration="0.045" />
  <viseme type="19" time="2.549" duration="0.089" />
  <viseme type="3" time="2.638" duration="0.119" />
  <viseme type="19" time="2.757" duration="0.029" />
  <viseme type="7" time="2.786" duration="0.039" />
  <viseme type="5" time="2.825" duration="0.063" />
  <viseme type="13" time="2.888" duration="0.04" />
  <viseme type="20" time="2.928" duration="0.139" />
  <viseme type="6" time="3.067" duration="0.079" />
  <viseme type="20" time="3.146" duration="0.169" />
</LipSyncVisemes>