<?xml version="1.0" encoding="utf-8"?>
<LipSyncVisemes wavFile="301217.wav">
  <viseme type="1" time="0.1" duration="0.12" />
  <viseme type="21" time="0.22" duration="0.09" />
  <viseme type="19" time="0.31" duration="0.07" />
  <viseme type="2" time="0.38" duration="0.12" />
  <viseme type="19" time="0.5" duration="0.095" />
  <viseme type="21" time="0.595" duration="0.08" />
  <viseme type="1" time="0.675" duration="0.18" />
  <viseme type="19" time="0.855" duration="0.1" />
  <viseme type="16" time="0.955" duration="0.1" />
</LipSyncVisemes>