<?xml version="1.0" encoding="utf-8"?>
<LipSyncVisemes wavFile="TTS-94BA7A30ADD807C84908D05688DEF098.wav">
  <viseme type="6" time="0.1" duration="0.085" />
  <viseme type="19" time="0.185" duration="0.05" />
  <viseme type="15" time="0.235" duration="0.07" />
  <viseme type="14" time="0.305" duration="0.055" />
  <viseme type="2" time="0.36" duration="0.055" />
  <viseme type="6" time="0.415" duration="0.055" />
  <viseme type="20" time="0.47" duration="0.08" />
  <viseme type="4" time="0.55" duration="0.09" />
  <viseme type="18" time="0.64" duration="0.08" />
  <viseme type="13" time="0.72" duration="0.065" />
  <viseme type="6" time="0.785" duration="0.055" />
  <viseme type="19" time="0.84" duration="0.1" />
  <viseme type="6" time="0.94" duration="0.065" />
  <viseme type="20" time="1.005" duration="0.07" />
  <viseme type="4" time="1.075" duration="0.13" />
  <viseme type="14" time="1.205" duration="0.115" />
  <viseme type="15" time="1.32" duration="0.2" />
  <viseme type="2" time="2.37" duration="0.125" />
  <viseme type="19" time="2.495" duration="0.115" />
  <viseme type="19" time="2.61" duration="0.07" />
  <viseme type="6" time="2.68" duration="0.055" />
  <viseme type="4" time="2.735" duration="0.06" />
  <viseme type="21" time="2.795" duration="0.09" />
  <viseme type="1" time="2.885" duration="0.105" />
  <viseme type="13" time="2.99" duration="0.08" />
  <viseme type="6" time="3.07" duration="0.075" />
  <viseme type="19" time="3.145" duration="0.08" />
  <viseme type="19" time="3.225" duration="0.13" />
  <viseme type="7" time="3.355" duration="0.2" />
  <viseme type="1" time="4.405" duration="0.075" />
  <viseme type="20" time="4.48" duration="0.08" />
  <viseme type="2" time="4.56" duration="0.057" />
  <viseme type="6" time="4.617" duration="0.057" />
  <viseme type="14" time="4.674" duration="0.09" />
  <viseme type="2" time="4.764" duration="0.097" />
  <viseme type="6" time="4.861" duration="0.097" />
  <viseme type="18" time="4.958" duration="0.08" />
  <viseme type="15" time="5.038" duration="0.09" />
  <viseme type="20" time="5.128" duration="0.08" />
  <viseme type="4" time="5.208" duration="0.1" />
  <viseme type="19" time="5.308" duration="0.07" />
  <viseme type="21" time="5.378" duration="0.085" />
  <viseme type="8" time="5.463" duration="0.07" />
  <viseme type="4" time="5.533" duration="0.07" />
  <viseme type="21" time="5.603" duration="0.065" />
  <viseme type="1" time="5.668" duration="0.055" />
  <viseme type="19" time="5.723" duration="0.075" />
  <viseme type="19" time="5.798" duration="0.04" />
  <viseme type="15" time="5.838" duration="0.085" />
  <viseme type="1" time="5.923" duration="0.09" />
  <viseme type="19" time="6.013" duration="0.07" />
  <viseme type="19" time="6.083" duration="0.04" />
  <viseme type="21" time="6.123" duration="0.06" />
  <viseme type="1" time="6.183" duration="0.2" />
  <viseme type="19" time="6.383" duration="0.065" />
  <viseme type="21" time="6.448" duration="0.085" />
  <viseme type="8" time="6.533" duration="0.072" />
  <viseme type="4" time="6.605" duration="0.072" />
  <viseme type="21" time="6.677" duration="0.075" />
  <viseme type="1" time="6.752" duration="0.07" />
  <viseme type="19" time="6.822" duration="0.09" />
  <viseme type="19" time="6.912" duration="0.04" />
  <viseme type="15" time="6.952" duration="0.2" />
  <viseme type="1" time="8.002" duration="0.075" />
  <viseme type="20" time="8.077" duration="0.085" />
  <viseme type="2" time="8.162" duration="0.097" />
  <viseme type="6" time="8.259" duration="0.097" />
  <viseme type="12" time="8.356" duration="0.08" />
  <viseme type="1" time="8.436" duration="0.09" />
  <viseme type="15" time="8.526" duration="0.095" />
  <viseme type="19" time="8.621" duration="0.07" />
  <viseme type="4" time="8.691" duration="0.06" />
  <viseme type="21" time="8.751" duration="0.09" />
  <viseme type="1" time="8.841" duration="0.13" />
  <viseme type="19" time="8.97100000000001" duration="0.06" />
  <viseme type="6" time="9.03100000000001" duration="0.12" />
  <viseme type="19" time="9.15100000000001" duration="0.1" />
  <viseme type="16" time="9.251" duration="0.1" />
</LipSyncVisemes>