<?xml version="1.0" encoding="utf-8"?>
<LipSyncVisemes wavFile="TTS-D6736FEC0FD69257ACA2BAFACBE57D89.wav">
  <viseme type="6" time="0.1" duration="0.085" />
  <viseme type="19" time="0.185" duration="0.065" />
  <viseme type="19" time="0.25" duration="0.04" />
  <viseme type="6" time="0.29" duration="0.06" />
  <viseme type="21" time="0.35" duration="0.095" />
  <viseme type="4" time="0.445" duration="0.165" />
  <viseme type="19" time="0.61" duration="0.06" />
  <viseme type="19" time="0.67" duration="0.04" />
  <viseme type="15" time="0.71" duration="0.14" />
  <viseme type="17" time="1.25" duration="0.055" />
  <viseme type="4" time="1.305" duration="0.055" />
  <viseme type="13" time="1.36" duration="0.085" />
  <viseme type="1" time="1.445" duration="0.065" />
  <viseme type="13" time="1.51" duration="0.055" />
  <viseme type="19" time="1.565" duration="0.065" />
  <viseme type="4" time="1.63" duration="0.1" />
  <viseme type="6" time="1.73" duration="0.1" />
  <viseme type="15" time="1.83" duration="0.18" />
</LipSyncVisemes>