<?xml version="1.0" encoding="utf-8"?>
<LipSyncVisemes wavFile="TTS-9D2A62745B5028173AF27B4CE1E68AA8.wav">
  <viseme type="15" time="0.1" duration="0.125" />
  <viseme type="8" time="0.225" duration="0.105" />
  <viseme type="6" time="0.33" duration="0.085" />
  <viseme type="7" time="0.415" duration="0.07" />
  <viseme type="14" time="0.485" duration="0.07" />
  <viseme type="2" time="0.555" duration="0.05" />
  <viseme type="6" time="0.605" duration="0.05" />
  <viseme type="20" time="0.655" duration="0.07" />
  <viseme type="21" time="0.725" duration="0.065" />
  <viseme type="1" time="0.79" duration="0.135" />
  <viseme type="15" time="0.925" duration="0.09" />
  <viseme type="20" time="1.015" duration="0.045" />
  <viseme type="6" time="1.06" duration="0.04" />
  <viseme type="19" time="1.1" duration="0.055" />
  <viseme type="21" time="1.155" duration="0.05" />
  <viseme type="3" time="1.205" duration="0.18" />
  <viseme type="14" time="1.385" duration="0.145" />
  <viseme type="2" time="2.38" duration="0.062" />
  <viseme type="6" time="2.442" duration="0.062" />
  <viseme type="6" time="2.504" duration="0.11" />
  <viseme type="7" time="2.614" duration="0.1" />
  <viseme type="15" time="2.714" duration="0.085" />
  <viseme type="19" time="2.799" duration="0.035" />
  <viseme type="19" time="2.834" duration="0.05" />
  <viseme type="4" time="2.884" duration="0.055" />
  <viseme type="21" time="2.939" duration="0.095" />
  <viseme type="14" time="3.034" duration="0.07" />
  <viseme type="4" time="3.104" duration="0.042" />
  <viseme type="6" time="3.146" duration="0.042" />
  <viseme type="19" time="3.188" duration="0.125" />
  <viseme type="7" time="3.313" duration="0.12" />
  <viseme type="7" time="3.433" duration="0.08" />
  <viseme type="4" time="3.513" duration="0.065" />
  <viseme type="19" time="3.578" duration="0.04" />
  <viseme type="2" time="3.618" duration="0.052" />
  <viseme type="6" time="3.67" duration="0.052" />
  <viseme type="7" time="3.722" duration="0.08" />
  <viseme type="1" time="3.802" duration="0.06" />
  <viseme type="15" time="3.862" duration="0.08" />
  <viseme type="6" time="3.942" duration="0.08" />
  <viseme type="1" time="4.022" duration="0.06" />
  <viseme type="20" time="4.082" duration="0.06" />
  <viseme type="20" time="4.142" duration="0.045" />
  <viseme type="1" time="4.187" duration="0.055" />
  <viseme type="13" time="4.242" duration="0.12" />
</LipSyncVisemes>